CHANGES.rst
DESCRIPTION.rst
LICENSE
MANIFEST.in
README.md
setup.py
src/wai.tfimageclass.egg-info/PKG-INFO
src/wai.tfimageclass.egg-info/SOURCES.txt
src/wai.tfimageclass.egg-info/dependency_links.txt
src/wai.tfimageclass.egg-info/entry_points.txt
src/wai.tfimageclass.egg-info/namespace_packages.txt
src/wai.tfimageclass.egg-info/requires.txt
src/wai.tfimageclass.egg-info/top_level.txt
src/wai/tfimageclass/__init__.py
src/wai/tfimageclass/predict/__init__.py
src/wai/tfimageclass/predict/label_image.py
src/wai/tfimageclass/predict/label_redis.py
src/wai/tfimageclass/predict/poll.py
src/wai/tfimageclass/train/__init__.py
src/wai/tfimageclass/train/export.py
src/wai/tfimageclass/train/retrain.py
src/wai/tfimageclass/train/stats.py
src/wai/tfimageclass/utils/__init__.py
src/wai/tfimageclass/utils/logging_utils.py
src/wai/tfimageclass/utils/prediction_utils.py
src/wai/tfimageclass/utils/train_utils.py