Metadata-Version: 2.1
Name: wai.tfimageclass
Version: 0.0.15
Summary: Image classification using tensorflow.
Home-page: https://github.com/waikato-datamining/tensorflow/tree/master/image_classification
Author: Peter Reutemann and TensorFlow Team
Author-email: fracpete@waikato.ac.nz
License: Apache 2.0 License
Platform: UNKNOWN
Classifier: Development Status :: 4 - Beta
Classifier: License :: OSI Approved :: Apache Software License
Classifier: Topic :: Scientific/Engineering :: Artificial Intelligence
Classifier: Programming Language :: Python :: 3
License-File: LICENSE
